<?xml version="1.0" encoding="ISO-8859-1"?><pnml>
<net id="Net-One" type="P/T net">
<token id="Default" enabled="true" red="0" green="0" blue="0"/>
<place id="InterbloqPzaB">
<graphics>
<position x="240.0" y="780.0"/>
</graphics>
<name>
<value>InterbloqPzaB</value>
<graphics>
<offset x="33.75" y="-5.0"/>
</graphics>
</name>
<initialMarking>
<value>Default,1</value>
<graphics>
<offset x="0.0" y="0.0"/>
</graphics>
</initialMarking>
<capacity>
<value>0</value>
</capacity>
</place>
<place id="m1">
<graphics>
<position x="300.0" y="795.0"/>
</graphics>
<name>
<value>m1</value>
<graphics>
<offset x="55.0" y="19.0"/>
</graphics>
</name>
<initialMarking>
<value>Default,1</value>
<graphics>
<offset x="0.0" y="0.0"/>
</graphics>
</initialMarking>
<capacity>
<value>0</value>
</capacity>
</place>
<place id="m2">
<graphics>
<position x="285.0" y="1005.0"/>
</graphics>
<name>
<value>m2</value>
<graphics>
<offset x="49.0" y="4.0"/>
</graphics>
</name>
<initialMarking>
<value>Default,1</value>
<graphics>
<offset x="0.0" y="0.0"/>
</graphics>
</initialMarking>
<capacity>
<value>0</value>
</capacity>
</place>
<place id="m3">
<graphics>
<position x="795.0" y="795.0"/>
</graphics>
<name>
<value>m3</value>
<graphics>
<offset x="64.0" y="16.0"/>
</graphics>
</name>
<initialMarking>
<value>Default,1</value>
<graphics>
<offset x="0.0" y="0.0"/>
</graphics>
</initialMarking>
<capacity>
<value>0</value>
</capacity>
</place>
<place id="m4">
<graphics>
<position x="795.0" y="990.0"/>
</graphics>
<name>
<value>m4</value>
<graphics>
<offset x="55.0" y="12.0"/>
</graphics>
</name>
<initialMarking>
<value>Default,1</value>
<graphics>
<offset x="0.0" y="0.0"/>
</graphics>
</initialMarking>
<capacity>
<value>0</value>
</capacity>
</place>
<place id="P10">
<graphics>
<position x="510.0" y="1215.0"/>
</graphics>
<name>
<value>P10</value>
<graphics>
<offset x="59.0" y="26.0"/>
</graphics>
</name>
<initialMarking>
<value>Default,10</value>
<graphics>
<offset x="0.0" y="0.0"/>
</graphics>
</initialMarking>
<capacity>
<value>0</value>
</capacity>
</place>
<place id="P11">
<graphics>
<position x="585.0" y="690.0"/>
</graphics>
<name>
<value>P11</value>
<graphics>
<offset x="57.0" y="20.0"/>
</graphics>
</name>
<initialMarking>
<value>Default,0</value>
<graphics>
<offset x="0.0" y="0.0"/>
</graphics>
</initialMarking>
<capacity>
<value>0</value>
</capacity>
</place>
<place id="P12">
<graphics>
<position x="465.0" y="795.0"/>
</graphics>
<name>
<value>P12</value>
<graphics>
<offset x="54.0" y="18.0"/>
</graphics>
</name>
<initialMarking>
<value>Default,0</value>
<graphics>
<offset x="0.0" y="0.0"/>
</graphics>
</initialMarking>
<capacity>
<value>0</value>
</capacity>
</place>
<place id="P13">
<graphics>
<position x="705.0" y="795.0"/>
</graphics>
<name>
<value>P13</value>
<graphics>
<offset x="55.0" y="12.0"/>
</graphics>
</name>
<initialMarking>
<value>Default,0</value>
<graphics>
<offset x="0.0" y="0.0"/>
</graphics>
</initialMarking>
<capacity>
<value>0</value>
</capacity>
</place>
<place id="P14">
<graphics>
<position x="465.0" y="885.0"/>
</graphics>
<name>
<value>P14</value>
<graphics>
<offset x="59.0" y="18.0"/>
</graphics>
</name>
<initialMarking>
<value>Default,0</value>
<graphics>
<offset x="0.0" y="0.0"/>
</graphics>
</initialMarking>
<capacity>
<value>0</value>
</capacity>
</place>
<place id="P15">
<graphics>
<position x="705.0" y="885.0"/>
</graphics>
<name>
<value>P15</value>
<graphics>
<offset x="60.0" y="11.0"/>
</graphics>
</name>
<initialMarking>
<value>Default,0</value>
<graphics>
<offset x="0.0" y="0.0"/>
</graphics>
</initialMarking>
<capacity>
<value>0</value>
</capacity>
</place>
<place id="P16">
<graphics>
<position x="465.0" y="990.0"/>
</graphics>
<name>
<value>P16</value>
<graphics>
<offset x="56.0" y="12.0"/>
</graphics>
</name>
<initialMarking>
<value>Default,0</value>
<graphics>
<offset x="0.0" y="0.0"/>
</graphics>
</initialMarking>
<capacity>
<value>0</value>
</capacity>
</place>
<place id="P17">
<graphics>
<position x="705.0" y="990.0"/>
</graphics>
<name>
<value>P17</value>
<graphics>
<offset x="64.0" y="13.0"/>
</graphics>
</name>
<initialMarking>
<value>Default,0</value>
<graphics>
<offset x="0.0" y="0.0"/>
</graphics>
</initialMarking>
<capacity>
<value>0</value>
</capacity>
</place>
<place id="P18">
<graphics>
<position x="585.0" y="1110.0"/>
</graphics>
<name>
<value>P18</value>
<graphics>
<offset x="57.0" y="17.0"/>
</graphics>
</name>
<initialMarking>
<value>Default,0</value>
<graphics>
<offset x="0.0" y="0.0"/>
</graphics>
</initialMarking>
<capacity>
<value>0</value>
</capacity>
</place>
<place id="P20">
<graphics>
<position x="75.0" y="900.0"/>
</graphics>
<name>
<value>P20</value>
<graphics>
<offset x="62.0" y="11.0"/>
</graphics>
</name>
<initialMarking>
<value>Default,50</value>
<graphics>
<offset x="0.0" y="0.0"/>
</graphics>
</initialMarking>
<capacity>
<value>0</value>
</capacity>
</place>
<place id="P21">
<graphics>
<position x="150.0" y="795.0"/>
</graphics>
<name>
<value>P21</value>
<graphics>
<offset x="62.0" y="19.0"/>
</graphics>
</name>
<initialMarking>
<value>Default,0</value>
<graphics>
<offset x="0.0" y="0.0"/>
</graphics>
</initialMarking>
<capacity>
<value>0</value>
</capacity>
</place>
<place id="P22">
<graphics>
<position x="150.0" y="885.0"/>
</graphics>
<name>
<value>P22</value>
<graphics>
<offset x="63.0" y="12.0"/>
</graphics>
</name>
<initialMarking>
<value>Default,0</value>
<graphics>
<offset x="0.0" y="0.0"/>
</graphics>
</initialMarking>
<capacity>
<value>0</value>
</capacity>
</place>
<place id="P23">
<graphics>
<position x="150.0" y="990.0"/>
</graphics>
<name>
<value>P23</value>
<graphics>
<offset x="63.0" y="21.0"/>
</graphics>
</name>
<initialMarking>
<value>Default,0</value>
<graphics>
<offset x="0.0" y="0.0"/>
</graphics>
</initialMarking>
<capacity>
<value>0</value>
</capacity>
</place>
<place id="P27">
<graphics>
<position x="1192.5" y="896.25"/>
</graphics>
<name>
<value>P27</value>
<graphics>
<offset x="0.0" y="0.0"/>
</graphics>
</name>
<initialMarking>
<value>Default,1</value>
<graphics>
<offset x="0.0" y="0.0"/>
</graphics>
</initialMarking>
<capacity>
<value>0</value>
</capacity>
</place>
<place id="P28">
<graphics>
<position x="330.0" y="930.0"/>
</graphics>
<name>
<value>P28</value>
<graphics>
<offset x="0.0" y="0.0"/>
</graphics>
</name>
<initialMarking>
<value>Default,1</value>
<graphics>
<offset x="0.0" y="0.0"/>
</graphics>
</initialMarking>
<capacity>
<value>0</value>
</capacity>
</place>
<place id="P29">
<graphics>
<position x="945.0" y="562.5"/>
</graphics>
<name>
<value>P29</value>
<graphics>
<offset x="0.0" y="0.0"/>
</graphics>
</name>
<initialMarking>
<value>Default,0</value>
<graphics>
<offset x="0.0" y="0.0"/>
</graphics>
</initialMarking>
<capacity>
<value>0</value>
</capacity>
</place>
<place id="P30">
<graphics>
<position x="1050.0" y="915.0"/>
</graphics>
<name>
<value>P30</value>
<graphics>
<offset x="0.0" y="0.0"/>
</graphics>
</name>
<initialMarking>
<value>Default,50</value>
<graphics>
<offset x="0.0" y="0.0"/>
</graphics>
</initialMarking>
<capacity>
<value>0</value>
</capacity>
</place>
<place id="P31">
<graphics>
<position x="945.0" y="1110.0"/>
</graphics>
<name>
<value>P31</value>
<graphics>
<offset x="62.0" y="16.0"/>
</graphics>
</name>
<initialMarking>
<value>Default,0</value>
<graphics>
<offset x="0.0" y="0.0"/>
</graphics>
</initialMarking>
<capacity>
<value>0</value>
</capacity>
</place>
<place id="P32">
<graphics>
<position x="945.0" y="990.0"/>
</graphics>
<name>
<value>P32</value>
<graphics>
<offset x="65.0" y="13.0"/>
</graphics>
</name>
<initialMarking>
<value>Default,0</value>
<graphics>
<offset x="0.0" y="0.0"/>
</graphics>
</initialMarking>
<capacity>
<value>0</value>
</capacity>
</place>
<place id="P33">
<graphics>
<position x="945.0" y="885.0"/>
</graphics>
<name>
<value>P33</value>
<graphics>
<offset x="62.0" y="14.0"/>
</graphics>
</name>
<initialMarking>
<value>Default,0</value>
<graphics>
<offset x="0.0" y="0.0"/>
</graphics>
</initialMarking>
<capacity>
<value>0</value>
</capacity>
</place>
<place id="P34">
<graphics>
<position x="945.0" y="780.0"/>
</graphics>
<name>
<value>P34</value>
<graphics>
<offset x="58.0" y="20.0"/>
</graphics>
</name>
<initialMarking>
<value>Default,0</value>
<graphics>
<offset x="0.0" y="0.0"/>
</graphics>
</initialMarking>
<capacity>
<value>0</value>
</capacity>
</place>
<place id="P35">
<graphics>
<position x="945.0" y="690.0"/>
</graphics>
<name>
<value>P35</value>
<graphics>
<offset x="53.0" y="18.0"/>
</graphics>
</name>
<initialMarking>
<value>Default,0</value>
<graphics>
<offset x="0.0" y="0.0"/>
</graphics>
</initialMarking>
<capacity>
<value>0</value>
</capacity>
</place>
<place id="P36">
<graphics>
<position x="615.0" y="1215.0"/>
</graphics>
<name>
<value>P36</value>
<graphics>
<offset x="0.0" y="0.0"/>
</graphics>
</name>
<initialMarking>
<value>Default,0</value>
<graphics>
<offset x="0.0" y="0.0"/>
</graphics>
</initialMarking>
<capacity>
<value>0</value>
</capacity>
</place>
<place id="P37">
<graphics>
<position x="150.0" y="1110.0"/>
</graphics>
<name>
<value>P37</value>
<graphics>
<offset x="0.0" y="0.0"/>
</graphics>
</name>
<initialMarking>
<value>Default,0</value>
<graphics>
<offset x="0.0" y="0.0"/>
</graphics>
</initialMarking>
<capacity>
<value>0</value>
</capacity>
</place>
<place id="r1">
<graphics>
<position x="795.0" y="690.0"/>
</graphics>
<name>
<value>r1</value>
<graphics>
<offset x="55.0" y="17.0"/>
</graphics>
</name>
<initialMarking>
<value>Default,1</value>
<graphics>
<offset x="0.0" y="0.0"/>
</graphics>
</initialMarking>
<capacity>
<value>0</value>
</capacity>
</place>
<place id="r2">
<graphics>
<position x="585.0" y="885.0"/>
</graphics>
<name>
<value>r2</value>
<graphics>
<offset x="49.0" y="37.0"/>
</graphics>
</name>
<initialMarking>
<value>Default,1</value>
<graphics>
<offset x="0.0" y="0.0"/>
</graphics>
</initialMarking>
<capacity>
<value>0</value>
</capacity>
</place>
<place id="r3">
<graphics>
<position x="795.0" y="1125.0"/>
</graphics>
<name>
<value>r3</value>
<graphics>
<offset x="50.0" y="10.0"/>
</graphics>
</name>
<initialMarking>
<value>Default,1</value>
<graphics>
<offset x="0.0" y="0.0"/>
</graphics>
</initialMarking>
<capacity>
<value>0</value>
</capacity>
</place>
<transition id="T0">
<graphics>
<position x="585.0" y="630.0"/>
</graphics>
<name>
<value>T0</value>
<graphics>
<offset x="47.0" y="0.0"/>
</graphics>
</name>
<orientation>
<value>90</value>
</orientation>
<rate>
<value>1.0</value>
</rate>
<timed>
<value>false</value>
</timed>
<infiniteServer>
<value>false</value>
</infiniteServer>
<priority>
<value>1</value>
</priority>
</transition>
<transition id="T11">
<graphics>
<position x="465.0" y="735.0"/>
</graphics>
<name>
<value>T11</value>
<graphics>
<offset x="45.0" y="34.0"/>
</graphics>
</name>
<orientation>
<value>90</value>
</orientation>
<rate>
<value>1.0</value>
</rate>
<timed>
<value>false</value>
</timed>
<infiniteServer>
<value>false</value>
</infiniteServer>
<priority>
<value>1</value>
</priority>
</transition>
<transition id="T12">
<graphics>
<position x="705.0" y="735.0"/>
</graphics>
<name>
<value>T12</value>
<graphics>
<offset x="53.0" y="10.0"/>
</graphics>
</name>
<orientation>
<value>90</value>
</orientation>
<rate>
<value>1.0</value>
</rate>
<timed>
<value>false</value>
</timed>
<infiniteServer>
<value>false</value>
</infiniteServer>
<priority>
<value>1</value>
</priority>
</transition>
<transition id="T13">
<graphics>
<position x="465.0" y="840.0"/>
</graphics>
<name>
<value>T13</value>
<graphics>
<offset x="39.0" y="36.0"/>
</graphics>
</name>
<orientation>
<value>90</value>
</orientation>
<rate>
<value>1.0</value>
</rate>
<timed>
<value>false</value>
</timed>
<infiniteServer>
<value>false</value>
</infiniteServer>
<priority>
<value>1</value>
</priority>
</transition>
<transition id="T15">
<graphics>
<position x="465.0" y="930.0"/>
</graphics>
<name>
<value>T15</value>
<graphics>
<offset x="58.0" y="22.0"/>
</graphics>
</name>
<orientation>
<value>90</value>
</orientation>
<rate>
<value>1.0</value>
</rate>
<timed>
<value>false</value>
</timed>
<infiniteServer>
<value>false</value>
</infiniteServer>
<priority>
<value>1</value>
</priority>
</transition>
<transition id="T16">
<graphics>
<position x="705.0" y="930.0"/>
</graphics>
<name>
<value>T16</value>
<graphics>
<offset x="53.0" y="31.0"/>
</graphics>
</name>
<orientation>
<value>90</value>
</orientation>
<rate>
<value>1.0</value>
</rate>
<timed>
<value>false</value>
</timed>
<infiniteServer>
<value>false</value>
</infiniteServer>
<priority>
<value>1</value>
</priority>
</transition>
<transition id="T17">
<graphics>
<position x="465.0" y="1050.0"/>
</graphics>
<name>
<value>T17</value>
<graphics>
<offset x="53.0" y="34.0"/>
</graphics>
</name>
<orientation>
<value>90</value>
</orientation>
<rate>
<value>1.0</value>
</rate>
<timed>
<value>false</value>
</timed>
<infiniteServer>
<value>false</value>
</infiniteServer>
<priority>
<value>1</value>
</priority>
</transition>
<transition id="T18">
<graphics>
<position x="705.0" y="1050.0"/>
</graphics>
<name>
<value>T18</value>
<graphics>
<offset x="51.0" y="30.0"/>
</graphics>
</name>
<orientation>
<value>90</value>
</orientation>
<rate>
<value>1.0</value>
</rate>
<timed>
<value>false</value>
</timed>
<infiniteServer>
<value>false</value>
</infiniteServer>
<priority>
<value>1</value>
</priority>
</transition>
<transition id="T19">
<graphics>
<position x="585.0" y="1155.0"/>
</graphics>
<name>
<value>T19</value>
<graphics>
<offset x="59.0" y="25.0"/>
</graphics>
</name>
<orientation>
<value>90</value>
</orientation>
<rate>
<value>1.0</value>
</rate>
<timed>
<value>false</value>
</timed>
<infiniteServer>
<value>false</value>
</infiniteServer>
<priority>
<value>1</value>
</priority>
</transition>
<transition id="T21">
<graphics>
<position x="150.0" y="735.0"/>
</graphics>
<name>
<value>T21</value>
<graphics>
<offset x="57.0" y="21.0"/>
</graphics>
</name>
<orientation>
<value>90</value>
</orientation>
<rate>
<value>1.0</value>
</rate>
<timed>
<value>false</value>
</timed>
<infiniteServer>
<value>false</value>
</infiniteServer>
<priority>
<value>1</value>
</priority>
</transition>
<transition id="T22">
<graphics>
<position x="150.0" y="840.0"/>
</graphics>
<name>
<value>T22</value>
<graphics>
<offset x="56.0" y="11.0"/>
</graphics>
</name>
<orientation>
<value>90</value>
</orientation>
<rate>
<value>1.0</value>
</rate>
<timed>
<value>false</value>
</timed>
<infiniteServer>
<value>false</value>
</infiniteServer>
<priority>
<value>1</value>
</priority>
</transition>
<transition id="T23">
<graphics>
<position x="150.0" y="930.0"/>
</graphics>
<name>
<value>T23</value>
<graphics>
<offset x="54.0" y="29.0"/>
</graphics>
</name>
<orientation>
<value>90</value>
</orientation>
<rate>
<value>1.0</value>
</rate>
<timed>
<value>false</value>
</timed>
<infiniteServer>
<value>false</value>
</infiniteServer>
<priority>
<value>1</value>
</priority>
</transition>
<transition id="T24">
<graphics>
<position x="150.0" y="1050.0"/>
</graphics>
<name>
<value>T24</value>
<graphics>
<offset x="59.0" y="37.0"/>
</graphics>
</name>
<orientation>
<value>90</value>
</orientation>
<rate>
<value>1.0</value>
</rate>
<timed>
<value>false</value>
</timed>
<infiniteServer>
<value>false</value>
</infiniteServer>
<priority>
<value>1</value>
</priority>
</transition>
<transition id="T3">
<graphics>
<position x="705.0" y="840.0"/>
</graphics>
<name>
<value>T3</value>
<graphics>
<offset x="-5.0" y="35.0"/>
</graphics>
</name>
<orientation>
<value>90</value>
</orientation>
<rate>
<value>1.0</value>
</rate>
<timed>
<value>false</value>
</timed>
<infiniteServer>
<value>false</value>
</infiniteServer>
<priority>
<value>1</value>
</priority>
</transition>
<transition id="T31">
<graphics>
<position x="945.0" y="1155.0"/>
</graphics>
<name>
<value>T31</value>
<graphics>
<offset x="61.0" y="34.0"/>
</graphics>
</name>
<orientation>
<value>90</value>
</orientation>
<rate>
<value>1.0</value>
</rate>
<timed>
<value>false</value>
</timed>
<infiniteServer>
<value>false</value>
</infiniteServer>
<priority>
<value>1</value>
</priority>
</transition>
<transition id="T32">
<graphics>
<position x="945.0" y="1050.0"/>
</graphics>
<name>
<value>T32</value>
<graphics>
<offset x="59.0" y="16.0"/>
</graphics>
</name>
<orientation>
<value>90</value>
</orientation>
<rate>
<value>1.0</value>
</rate>
<timed>
<value>false</value>
</timed>
<infiniteServer>
<value>false</value>
</infiniteServer>
<priority>
<value>1</value>
</priority>
</transition>
<transition id="T33">
<graphics>
<position x="945.0" y="930.0"/>
</graphics>
<name>
<value>T33</value>
<graphics>
<offset x="60.0" y="16.0"/>
</graphics>
</name>
<orientation>
<value>90</value>
</orientation>
<rate>
<value>1.0</value>
</rate>
<timed>
<value>false</value>
</timed>
<infiniteServer>
<value>false</value>
</infiniteServer>
<priority>
<value>1</value>
</priority>
</transition>
<transition id="T34">
<graphics>
<position x="945.0" y="840.0"/>
</graphics>
<name>
<value>T34</value>
<graphics>
<offset x="57.0" y="19.0"/>
</graphics>
</name>
<orientation>
<value>90</value>
</orientation>
<rate>
<value>1.0</value>
</rate>
<timed>
<value>false</value>
</timed>
<infiniteServer>
<value>false</value>
</infiniteServer>
<priority>
<value>1</value>
</priority>
</transition>
<transition id="T35">
<graphics>
<position x="945.0" y="735.0"/>
</graphics>
<name>
<value>T35</value>
<graphics>
<offset x="55.0" y="22.0"/>
</graphics>
</name>
<orientation>
<value>90</value>
</orientation>
<rate>
<value>1.0</value>
</rate>
<timed>
<value>false</value>
</timed>
<infiniteServer>
<value>false</value>
</infiniteServer>
<priority>
<value>1</value>
</priority>
</transition>
<transition id="T36">
<graphics>
<position x="945.0" y="645.0"/>
</graphics>
<name>
<value>T36</value>
<graphics>
<offset x="23.0" y="5.0"/>
</graphics>
</name>
<orientation>
<value>90</value>
</orientation>
<rate>
<value>1.0</value>
</rate>
<timed>
<value>false</value>
</timed>
<infiniteServer>
<value>false</value>
</infiniteServer>
<priority>
<value>1</value>
</priority>
</transition>
<arc id="InterbloqPzaB to T21" source="InterbloqPzaB" target="T21">
<graphics/>
<inscription>
<value>Default,1</value>
<graphics/>
</inscription>
<tagged>
<value>false</value>
</tagged>
<arcpath id="000" x="237" y="782" curvePoint="false"/>
<arcpath id="001" x="175" y="746" curvePoint="false"/>
<type value="normal"/>
</arc>
<arc id="m1 to T11" source="m1" target="T11">
<graphics/>
<inscription>
<value>Default,1</value>
<graphics/>
</inscription>
<tagged>
<value>false</value>
</tagged>
<arcpath id="000" x="320" y="793" curvePoint="false"/>
<arcpath id="001" x="356" y="746" curvePoint="false"/>
<arcpath id="002" x="460" y="746" curvePoint="false"/>
<type value="normal"/>
</arc>
<arc id="m2 to T22" source="m2" target="T22">
<graphics/>
<inscription>
<value>Default,1</value>
<graphics/>
</inscription>
<tagged>
<value>false</value>
</tagged>
<arcpath id="000" x="286" y="1003" curvePoint="false"/>
<arcpath id="001" x="216" y="916" curvePoint="false"/>
<arcpath id="002" x="165" y="856" curvePoint="false"/>
<type value="normal"/>
</arc>
<arc id="m2 to T6" source="m2" target="T15">
<graphics/>
<inscription>
<value>Default,1</value>
<graphics/>
</inscription>
<tagged>
<value>false</value>
</tagged>
<arcpath id="000" x="308" y="1010" curvePoint="false"/>
<arcpath id="001" x="460" y="941" curvePoint="false"/>
<type value="normal"/>
</arc>
<arc id="m3 to T12" source="m3" target="T34">
<graphics/>
<inscription>
<value>Default,1</value>
<graphics/>
</inscription>
<tagged>
<value>false</value>
</tagged>
<arcpath id="000" x="820" y="810" curvePoint="false"/>
<arcpath id="001" x="940" y="851" curvePoint="false"/>
<type value="normal"/>
</arc>
<arc id="m3 to T12" source="m3" target="T12">
<graphics/>
<inscription>
<value>Default,1</value>
<graphics/>
</inscription>
<tagged>
<value>false</value>
</tagged>
<arcpath id="000" x="797" y="793" curvePoint="false"/>
<arcpath id="001" x="776" y="761" curvePoint="false"/>
<arcpath id="002" x="730" y="746" curvePoint="false"/>
<type value="normal"/>
</arc>
<arc id="m4 to T16" source="m4" target="T16">
<graphics/>
<inscription>
<value>Default,1</value>
<graphics/>
</inscription>
<tagged>
<value>false</value>
</tagged>
<arcpath id="000" x="796" y="988" curvePoint="false"/>
<arcpath id="001" x="761" y="941" curvePoint="false"/>
<arcpath id="002" x="730" y="941" curvePoint="false"/>
<type value="normal"/>
</arc>
<arc id="m4 to T32" source="m4" target="T32">
<graphics/>
<inscription>
<value>Default,1</value>
<graphics/>
</inscription>
<tagged>
<value>false</value>
</tagged>
<arcpath id="000" x="817" y="1008" curvePoint="false"/>
<arcpath id="001" x="891" y="1061" curvePoint="false"/>
<arcpath id="002" x="940" y="1061" curvePoint="false"/>
<type value="normal"/>
</arc>
<arc id="P10 to T0" source="P10" target="T0">
<graphics/>
<inscription>
<value>Default,1</value>
<graphics/>
</inscription>
<tagged>
<value>false</value>
</tagged>
<arcpath id="000" x="506" y="1225" curvePoint="false"/>
<arcpath id="001" x="45" y="1216" curvePoint="false"/>
<arcpath id="002" x="45" y="646" curvePoint="false"/>
<arcpath id="003" x="580" y="641" curvePoint="false"/>
<type value="normal"/>
</arc>
<arc id="P10 to T10" source="P35" target="T36">
<graphics/>
<inscription>
<value>Default,1</value>
<graphics/>
</inscription>
<tagged>
<value>false</value>
</tagged>
<arcpath id="000" x="941" y="701" curvePoint="false"/>
<arcpath id="001" x="951" y="701" curvePoint="false"/>
<arcpath id="002" x="955" y="660" curvePoint="false"/>
<type value="normal"/>
</arc>
<arc id="P11 to T11" source="P34" target="T35">
<graphics/>
<inscription>
<value>Default,1</value>
<graphics/>
</inscription>
<tagged>
<value>false</value>
</tagged>
<arcpath id="000" x="955" y="776" curvePoint="false"/>
<arcpath id="001" x="955" y="750" curvePoint="false"/>
<type value="normal"/>
</arc>
<arc id="P11 to T11" source="P11" target="T11">
<graphics/>
<inscription>
<value>Default,1</value>
<graphics/>
</inscription>
<tagged>
<value>false</value>
</tagged>
<arcpath id="000" x="585" y="711" curvePoint="false"/>
<arcpath id="001" x="551" y="746" curvePoint="false"/>
<arcpath id="002" x="490" y="746" curvePoint="false"/>
<type value="normal"/>
</arc>
<arc id="P11 to T12" source="P11" target="T12">
<graphics/>
<inscription>
<value>Default,1</value>
<graphics/>
</inscription>
<tagged>
<value>false</value>
</tagged>
<arcpath id="000" x="606" y="711" curvePoint="false"/>
<arcpath id="001" x="641" y="746" curvePoint="false"/>
<arcpath id="002" x="700" y="746" curvePoint="false"/>
<type value="normal"/>
</arc>
<arc id="P12 to T12" source="P33" target="T34">
<graphics/>
<inscription>
<value>Default,1</value>
<graphics/>
</inscription>
<tagged>
<value>false</value>
</tagged>
<arcpath id="000" x="955" y="881" curvePoint="false"/>
<arcpath id="001" x="955" y="855" curvePoint="false"/>
<type value="normal"/>
</arc>
<arc id="P13 to T13" source="P32" target="T33">
<graphics/>
<inscription>
<value>Default,1</value>
<graphics/>
</inscription>
<tagged>
<value>false</value>
</tagged>
<arcpath id="000" x="955" y="986" curvePoint="false"/>
<arcpath id="001" x="955" y="945" curvePoint="false"/>
<type value="normal"/>
</arc>
<arc id="P14 to T14" source="P31" target="T32">
<graphics/>
<inscription>
<value>Default,1</value>
<graphics/>
</inscription>
<tagged>
<value>false</value>
</tagged>
<arcpath id="000" x="955" y="1106" curvePoint="false"/>
<arcpath id="001" x="955" y="1065" curvePoint="false"/>
<type value="normal"/>
</arc>
<arc id="P1 to T9" source="P18" target="T19">
<graphics/>
<inscription>
<value>Default,1</value>
<graphics/>
</inscription>
<tagged>
<value>false</value>
</tagged>
<arcpath id="000" x="595" y="1135" curvePoint="false"/>
<arcpath id="001" x="595" y="1160" curvePoint="false"/>
<type value="normal"/>
</arc>
<arc id="P20 to T17" source="P21" target="T22">
<graphics/>
<inscription>
<value>Default,1</value>
<graphics/>
</inscription>
<tagged>
<value>false</value>
</tagged>
<arcpath id="000" x="160" y="820" curvePoint="false"/>
<arcpath id="001" x="160" y="845" curvePoint="false"/>
<type value="normal"/>
</arc>
<arc id="P21 to T18" source="P22" target="T23">
<graphics/>
<inscription>
<value>Default,1</value>
<graphics/>
</inscription>
<tagged>
<value>false</value>
</tagged>
<arcpath id="000" x="160" y="910" curvePoint="false"/>
<arcpath id="001" x="160" y="935" curvePoint="false"/>
<type value="normal"/>
</arc>
<arc id="P22 to T19" source="P23" target="T24">
<graphics/>
<inscription>
<value>Default,1</value>
<graphics/>
</inscription>
<tagged>
<value>false</value>
</tagged>
<arcpath id="000" x="160" y="1015" curvePoint="false"/>
<arcpath id="001" x="160" y="1055" curvePoint="false"/>
<type value="normal"/>
</arc>
<arc id="P25 to T16" source="P20" target="T21">
<graphics/>
<inscription>
<value>Default,1</value>
<graphics/>
</inscription>
<tagged>
<value>false</value>
</tagged>
<arcpath id="000" x="86" y="896" curvePoint="false"/>
<arcpath id="001" x="86" y="746" curvePoint="false"/>
<arcpath id="002" x="145" y="746" curvePoint="false"/>
<type value="normal"/>
</arc>
<arc id="P27 to T12" source="P27" target="T12">
<graphics/>
<inscription>
<value>Default,1</value>
<graphics/>
</inscription>
<tagged>
<value>false</value>
</tagged>
<arcpath id="000" x="1203" y="892" curvePoint="false"/>
<arcpath id="001" x="1226" y="555" curvePoint="false"/>
<arcpath id="002" x="791" y="555" curvePoint="false"/>
<arcpath id="003" x="720" y="741" curvePoint="false"/>
<type value="normal"/>
</arc>
<arc id="P27 to T31" source="P27" target="T31">
<graphics/>
<inscription>
<value>Default,1</value>
<graphics/>
</inscription>
<tagged>
<value>false</value>
</tagged>
<arcpath id="000" x="1198" y="921" curvePoint="false"/>
<arcpath id="001" x="1121" y="1196" curvePoint="false"/>
<arcpath id="002" x="951" y="1196" curvePoint="false"/>
<arcpath id="003" x="955" y="1170" curvePoint="false"/>
<type value="normal"/>
</arc>
<arc id="P28 to T13" source="P28" target="T13">
<graphics/>
<inscription>
<value>Default,1</value>
<graphics/>
</inscription>
<tagged>
<value>false</value>
</tagged>
<arcpath id="000" x="353" y="932" curvePoint="false"/>
<arcpath id="001" x="470" y="855" curvePoint="false"/>
<type value="normal"/>
</arc>
<arc id="P28 to T22" source="P28" target="T22">
<graphics/>
<inscription>
<value>Default,1</value>
<graphics/>
</inscription>
<tagged>
<value>false</value>
</tagged>
<arcpath id="000" x="327" y="933" curvePoint="false"/>
<arcpath id="001" x="175" y="851" curvePoint="false"/>
<type value="normal"/>
</arc>
<arc id="P2 to T8" source="P16" target="T17">
<graphics/>
<inscription>
<value>Default,1</value>
<graphics/>
</inscription>
<tagged>
<value>false</value>
</tagged>
<arcpath id="000" x="475" y="1015" curvePoint="false"/>
<arcpath id="001" x="475" y="1055" curvePoint="false"/>
<type value="normal"/>
</arc>
<arc id="P30 to T31" source="P30" target="T31">
<graphics/>
<inscription>
<value>Default,1</value>
<graphics/>
</inscription>
<tagged>
<value>false</value>
</tagged>
<arcpath id="000" x="1060" y="940" curvePoint="false"/>
<arcpath id="001" x="1056" y="1166" curvePoint="false"/>
<arcpath id="002" x="970" y="1166" curvePoint="false"/>
<type value="normal"/>
</arc>
<arc id="P3 to T7" source="P17" target="T18">
<graphics/>
<inscription>
<value>Default,1</value>
<graphics/>
</inscription>
<tagged>
<value>false</value>
</tagged>
<arcpath id="000" x="715" y="1015" curvePoint="false"/>
<arcpath id="001" x="715" y="1055" curvePoint="false"/>
<type value="normal"/>
</arc>
<arc id="P4 to T5" source="P15" target="T16">
<graphics/>
<inscription>
<value>Default,1</value>
<graphics/>
</inscription>
<tagged>
<value>false</value>
</tagged>
<arcpath id="000" x="715" y="910" curvePoint="false"/>
<arcpath id="001" x="715" y="935" curvePoint="false"/>
<type value="normal"/>
</arc>
<arc id="P5 to T6" source="P14" target="T15">
<graphics/>
<inscription>
<value>Default,1</value>
<graphics/>
</inscription>
<tagged>
<value>false</value>
</tagged>
<arcpath id="000" x="475" y="910" curvePoint="false"/>
<arcpath id="001" x="475" y="935" curvePoint="false"/>
<type value="normal"/>
</arc>
<arc id="P6 to T4" source="P12" target="T13">
<graphics/>
<inscription>
<value>Default,1</value>
<graphics/>
</inscription>
<tagged>
<value>false</value>
</tagged>
<arcpath id="000" x="475" y="820" curvePoint="false"/>
<arcpath id="001" x="475" y="845" curvePoint="false"/>
<type value="normal"/>
</arc>
<arc id="P7 to T3" source="P13" target="T3">
<graphics/>
<inscription>
<value>Default,1</value>
<graphics/>
</inscription>
<tagged>
<value>false</value>
</tagged>
<arcpath id="000" x="715" y="820" curvePoint="false"/>
<arcpath id="001" x="715" y="845" curvePoint="false"/>
<type value="normal"/>
</arc>
<arc id="r1 to T0" source="r1" target="T0">
<graphics/>
<inscription>
<value>Default,1</value>
<graphics/>
</inscription>
<tagged>
<value>false</value>
</tagged>
<arcpath id="000" x="793" y="691" curvePoint="false"/>
<arcpath id="001" x="731" y="641" curvePoint="false"/>
<arcpath id="002" x="610" y="641" curvePoint="false"/>
<type value="normal"/>
</arc>
<arc id="r1 to T35" source="r1" target="T35">
<graphics/>
<inscription>
<value>Default,1</value>
<graphics/>
</inscription>
<tagged>
<value>false</value>
</tagged>
<arcpath id="000" x="818" y="707" curvePoint="false"/>
<arcpath id="001" x="891" y="746" curvePoint="false"/>
<arcpath id="002" x="940" y="746" curvePoint="false"/>
<type value="normal"/>
</arc>
<arc id="r2 to T21" source="r2" target="T21">
<graphics/>
<inscription>
<value>Default,1</value>
<graphics/>
</inscription>
<tagged>
<value>false</value>
</tagged>
<arcpath id="000" x="587" y="882" curvePoint="false"/>
<arcpath id="001" x="476" y="701" curvePoint="false"/>
<arcpath id="002" x="161" y="701" curvePoint="false"/>
<arcpath id="003" x="160" y="740" curvePoint="false"/>
<type value="normal"/>
</arc>
<arc id="r2 to T23" source="r2" target="T23">
<graphics/>
<inscription>
<value>Default,1</value>
<graphics/>
</inscription>
<tagged>
<value>false</value>
</tagged>
<arcpath id="000" x="590" y="910" curvePoint="false"/>
<arcpath id="001" x="566" y="971" curvePoint="false"/>
<arcpath id="002" x="281" y="971" curvePoint="false"/>
<arcpath id="003" x="175" y="941" curvePoint="false"/>
<type value="normal"/>
</arc>
<arc id="r2 to T3" source="r2" target="T3">
<graphics/>
<inscription>
<value>Default,1</value>
<graphics/>
</inscription>
<tagged>
<value>false</value>
</tagged>
<arcpath id="000" x="603" y="883" curvePoint="false"/>
<arcpath id="001" x="626" y="851" curvePoint="false"/>
<arcpath id="002" x="700" y="851" curvePoint="false"/>
<type value="normal"/>
</arc>
<arc id="r2 to T33" source="r2" target="T33">
<graphics/>
<inscription>
<value>Default,1</value>
<graphics/>
</inscription>
<tagged>
<value>false</value>
</tagged>
<arcpath id="000" x="610" y="898" curvePoint="false"/>
<arcpath id="001" x="791" y="941" curvePoint="false"/>
<arcpath id="002" x="940" y="941" curvePoint="false"/>
<type value="normal"/>
</arc>
<arc id="r2 to T4" source="r2" target="T13">
<graphics/>
<inscription>
<value>Default,1</value>
<graphics/>
</inscription>
<tagged>
<value>false</value>
</tagged>
<arcpath id="000" x="581" y="890" curvePoint="false"/>
<arcpath id="001" x="490" y="851" curvePoint="false"/>
<type value="normal"/>
</arc>
<arc id="r3 to T15" source="r3" target="T31">
<graphics/>
<inscription>
<value>Default,1</value>
<graphics/>
</inscription>
<tagged>
<value>false</value>
</tagged>
<arcpath id="000" x="820" y="1138" curvePoint="false"/>
<arcpath id="001" x="940" y="1166" curvePoint="false"/>
<type value="normal"/>
</arc>
<arc id="r3 to T17" source="r3" target="T17">
<graphics/>
<inscription>
<value>Default,1</value>
<graphics/>
</inscription>
<tagged>
<value>false</value>
</tagged>
<arcpath id="000" x="791" y="1136" curvePoint="false"/>
<arcpath id="001" x="686" y="1136" curvePoint="false"/>
<arcpath id="002" x="596" y="1061" curvePoint="false"/>
<arcpath id="003" x="490" y="1061" curvePoint="false"/>
<type value="normal"/>
</arc>
<arc id="r3 to T18" source="r3" target="T18">
<graphics/>
<inscription>
<value>Default,1</value>
<graphics/>
</inscription>
<tagged>
<value>false</value>
</tagged>
<arcpath id="000" x="791" y="1130" curvePoint="false"/>
<arcpath id="001" x="731" y="1106" curvePoint="false"/>
<arcpath id="002" x="716" y="1091" curvePoint="false"/>
<arcpath id="003" x="710" y="1065" curvePoint="false"/>
<type value="normal"/>
</arc>
<arc id="T0 to P8" source="T0" target="P11">
<graphics/>
<inscription>
<value>Default,1</value>
<graphics/>
</inscription>
<tagged>
<value>false</value>
</tagged>
<arcpath id="000" x="595" y="645" curvePoint="false"/>
<arcpath id="001" x="595" y="686" curvePoint="false"/>
<type value="normal"/>
</arc>
<arc id="T11 to P10" source="T35" target="P35">
<graphics/>
<inscription>
<value>Default,1</value>
<graphics/>
</inscription>
<tagged>
<value>false</value>
</tagged>
<arcpath id="000" x="955" y="740" curvePoint="false"/>
<arcpath id="001" x="955" y="715" curvePoint="false"/>
<type value="normal"/>
</arc>
<arc id="T11 to r1" source="T11" target="r1">
<graphics/>
<inscription>
<value>Default,1</value>
<graphics/>
</inscription>
<tagged>
<value>false</value>
</tagged>
<arcpath id="000" x="475" y="740" curvePoint="false"/>
<arcpath id="001" x="506" y="671" curvePoint="false"/>
<arcpath id="002" x="746" y="671" curvePoint="false"/>
<arcpath id="003" x="792" y="693" curvePoint="false"/>
<type value="normal"/>
</arc>
<arc id="T12 to P11" source="T34" target="P34">
<graphics/>
<inscription>
<value>Default,1</value>
<graphics/>
</inscription>
<tagged>
<value>false</value>
</tagged>
<arcpath id="000" x="955" y="845" curvePoint="false"/>
<arcpath id="001" x="955" y="805" curvePoint="false"/>
<type value="normal"/>
</arc>
<arc id="T12 to r1" source="T12" target="r1">
<graphics/>
<inscription>
<value>Default,1</value>
<graphics/>
</inscription>
<tagged>
<value>false</value>
</tagged>
<arcpath id="000" x="710" y="740" curvePoint="false"/>
<arcpath id="001" x="716" y="731" curvePoint="false"/>
<arcpath id="002" x="776" y="731" curvePoint="false"/>
<arcpath id="003" x="795" y="711" curvePoint="false"/>
<type value="normal"/>
</arc>
<arc id="T13 to m1" source="T13" target="m1">
<graphics/>
<inscription>
<value>Default,1</value>
<graphics/>
</inscription>
<tagged>
<value>false</value>
</tagged>
<arcpath id="000" x="460" y="851" curvePoint="false"/>
<arcpath id="001" x="356" y="851" curvePoint="false"/>
<arcpath id="002" x="321" y="816" curvePoint="false"/>
<type value="normal"/>
</arc>
<arc id="T13 to P12" source="T33" target="P33">
<graphics/>
<inscription>
<value>Default,1</value>
<graphics/>
</inscription>
<tagged>
<value>false</value>
</tagged>
<arcpath id="000" x="955" y="935" curvePoint="false"/>
<arcpath id="001" x="955" y="910" curvePoint="false"/>
<type value="normal"/>
</arc>
<arc id="T14 to P13" source="T32" target="P32">
<graphics/>
<inscription>
<value>Default,1</value>
<graphics/>
</inscription>
<tagged>
<value>false</value>
</tagged>
<arcpath id="000" x="955" y="1055" curvePoint="false"/>
<arcpath id="001" x="955" y="1015" curvePoint="false"/>
<type value="normal"/>
</arc>
<arc id="T15 to P14" source="T31" target="P31">
<graphics/>
<inscription>
<value>Default,1</value>
<graphics/>
</inscription>
<tagged>
<value>false</value>
</tagged>
<arcpath id="000" x="955" y="1160" curvePoint="false"/>
<arcpath id="001" x="955" y="1135" curvePoint="false"/>
<type value="normal"/>
</arc>
<arc id="T15 to P28" source="T15" target="P28">
<graphics/>
<inscription>
<value>Default,1</value>
<graphics/>
</inscription>
<tagged>
<value>false</value>
</tagged>
<arcpath id="000" x="460" y="941" curvePoint="false"/>
<arcpath id="001" x="356" y="941" curvePoint="false"/>
<type value="normal"/>
</arc>
<arc id="T16 to P20" source="T21" target="P21">
<graphics/>
<inscription>
<value>Default,1</value>
<graphics/>
</inscription>
<tagged>
<value>false</value>
</tagged>
<arcpath id="000" x="160" y="750" curvePoint="false"/>
<arcpath id="001" x="160" y="791" curvePoint="false"/>
<type value="normal"/>
</arc>
<arc id="T16 to r2" source="T16" target="r2">
<graphics/>
<inscription>
<value>Default,1</value>
<graphics/>
</inscription>
<tagged>
<value>false</value>
</tagged>
<arcpath id="000" x="700" y="941" curvePoint="false"/>
<arcpath id="001" x="626" y="941" curvePoint="false"/>
<arcpath id="002" x="603" y="907" curvePoint="false"/>
<type value="normal"/>
</arc>
<arc id="T17 to m2" source="T17" target="m2">
<graphics/>
<inscription>
<value>Default,1</value>
<graphics/>
</inscription>
<tagged>
<value>false</value>
</tagged>
<arcpath id="000" x="460" y="1061" curvePoint="false"/>
<arcpath id="001" x="356" y="1061" curvePoint="false"/>
<arcpath id="002" x="307" y="1025" curvePoint="false"/>
<type value="normal"/>
</arc>
<arc id="T17 to P18" source="T17" target="P18">
<graphics/>
<inscription>
<value>Default,1</value>
<graphics/>
</inscription>
<tagged>
<value>false</value>
</tagged>
<arcpath id="000" x="475" y="1065" curvePoint="false"/>
<arcpath id="001" x="476" y="1091" curvePoint="false"/>
<arcpath id="002" x="581" y="1117" curvePoint="false"/>
<type value="normal"/>
</arc>
<arc id="T17 to P21" source="T22" target="P22">
<graphics/>
<inscription>
<value>Default,1</value>
<graphics/>
</inscription>
<tagged>
<value>false</value>
</tagged>
<arcpath id="000" x="155" y="855" curvePoint="false"/>
<arcpath id="001" x="158" y="881" curvePoint="false"/>
<type value="normal"/>
</arc>
<arc id="T18 to m2" source="T23" target="m2">
<graphics/>
<inscription>
<value>Default,1</value>
<graphics/>
</inscription>
<tagged>
<value>false</value>
</tagged>
<arcpath id="000" x="175" y="941" curvePoint="false"/>
<arcpath id="001" x="282" y="1007" curvePoint="false"/>
<type value="normal"/>
</arc>
<arc id="T18 to m4" source="T18" target="m4">
<graphics/>
<inscription>
<value>Default,1</value>
<graphics/>
</inscription>
<tagged>
<value>false</value>
</tagged>
<arcpath id="000" x="730" y="1061" curvePoint="false"/>
<arcpath id="001" x="776" y="1061" curvePoint="false"/>
<arcpath id="002" x="798" y="1013" curvePoint="false"/>
<type value="normal"/>
</arc>
<arc id="T18 to P18" source="T18" target="P18">
<graphics/>
<inscription>
<value>Default,1</value>
<graphics/>
</inscription>
<tagged>
<value>false</value>
</tagged>
<arcpath id="000" x="700" y="1061" curvePoint="false"/>
<arcpath id="001" x="641" y="1061" curvePoint="false"/>
<arcpath id="002" x="605" y="1108" curvePoint="false"/>
<type value="normal"/>
</arc>
<arc id="T18 to P22" source="T23" target="P23">
<graphics/>
<inscription>
<value>Default,1</value>
<graphics/>
</inscription>
<tagged>
<value>false</value>
</tagged>
<arcpath id="000" x="160" y="945" curvePoint="false"/>
<arcpath id="001" x="160" y="986" curvePoint="false"/>
<type value="normal"/>
</arc>
<arc id="T19 to P10" source="T19" target="P10">
<graphics/>
<inscription>
<value>Default,1</value>
<graphics/>
</inscription>
<tagged>
<value>false</value>
</tagged>
<arcpath id="000" x="590" y="1170" curvePoint="false"/>
<arcpath id="001" x="532" y="1216" curvePoint="false"/>
<type value="normal"/>
</arc>
<arc id="T19 to P36" source="T19" target="P36">
<graphics/>
<inscription>
<value>Default,1</value>
<graphics/>
</inscription>
<tagged>
<value>false</value>
</tagged>
<arcpath id="000" x="600" y="1171" curvePoint="false"/>
<arcpath id="001" x="618" y="1212" curvePoint="false"/>
<type value="normal"/>
</arc>
<arc id="T19 to r3" source="T19" target="r3">
<graphics/>
<inscription>
<value>Default,1</value>
<graphics/>
</inscription>
<tagged>
<value>false</value>
</tagged>
<arcpath id="000" x="610" y="1166" curvePoint="false"/>
<arcpath id="001" x="746" y="1166" curvePoint="false"/>
<arcpath id="002" x="792" y="1142" curvePoint="false"/>
<type value="normal"/>
</arc>
<arc id="T1 to P7" source="T12" target="P13">
<graphics/>
<inscription>
<value>Default,1</value>
<graphics/>
</inscription>
<tagged>
<value>false</value>
</tagged>
<arcpath id="000" x="715" y="750" curvePoint="false"/>
<arcpath id="001" x="715" y="791" curvePoint="false"/>
<type value="normal"/>
</arc>
<arc id="T22 to r2" source="T22" target="r2">
<graphics/>
<inscription>
<value>Default,1</value>
<graphics/>
</inscription>
<tagged>
<value>false</value>
</tagged>
<arcpath id="000" x="175" y="851" curvePoint="false"/>
<arcpath id="001" x="341" y="851" curvePoint="false"/>
<arcpath id="002" x="371" y="836" curvePoint="false"/>
<arcpath id="003" x="521" y="836" curvePoint="false"/>
<arcpath id="004" x="583" y="886" curvePoint="false"/>
<type value="normal"/>
</arc>
<arc id="T23 to InterbloqPzaB" source="T23" target="InterbloqPzaB">
<graphics/>
<inscription>
<value>Default,1</value>
<graphics/>
</inscription>
<tagged>
<value>false</value>
</tagged>
<arcpath id="000" x="175" y="941" curvePoint="false"/>
<arcpath id="001" x="240" y="915" curvePoint="false"/>
<arcpath id="002" x="248" y="805" curvePoint="false"/>
<type value="normal"/>
</arc>
<arc id="T23 to P28" source="T23" target="P28">
<graphics/>
<inscription>
<value>Default,1</value>
<graphics/>
</inscription>
<tagged>
<value>false</value>
</tagged>
<arcpath id="000" x="175" y="941" curvePoint="false"/>
<arcpath id="001" x="326" y="941" curvePoint="false"/>
<type value="normal"/>
</arc>
<arc id="T24 to P20" source="T24" target="P20">
<graphics/>
<inscription>
<value>Default,1</value>
<graphics/>
</inscription>
<tagged>
<value>false</value>
</tagged>
<arcpath id="000" x="145" y="1061" curvePoint="false"/>
<arcpath id="001" x="86" y="1061" curvePoint="false"/>
<arcpath id="002" x="86" y="926" curvePoint="false"/>
<type value="normal"/>
</arc>
<arc id="T24 to P37" source="T24" target="P37">
<graphics/>
<inscription>
<value>Default,1</value>
<graphics/>
</inscription>
<tagged>
<value>false</value>
</tagged>
<arcpath id="000" x="155" y="1065" curvePoint="false"/>
<arcpath id="001" x="158" y="1106" curvePoint="false"/>
<type value="normal"/>
</arc>
<arc id="T24 to r2" source="T24" target="r2">
<graphics/>
<inscription>
<value>Default,1</value>
<graphics/>
</inscription>
<tagged>
<value>false</value>
</tagged>
<arcpath id="000" x="175" y="1061" curvePoint="false"/>
<arcpath id="001" x="296" y="1061" curvePoint="false"/>
<arcpath id="002" x="311" y="1046" curvePoint="false"/>
<arcpath id="003" x="326" y="1031" curvePoint="false"/>
<arcpath id="004" x="596" y="1031" curvePoint="false"/>
<arcpath id="005" x="596" y="911" curvePoint="false"/>
<type value="normal"/>
</arc>
<arc id="T2 to P6" source="T11" target="P12">
<graphics/>
<inscription>
<value>Default,1</value>
<graphics/>
</inscription>
<tagged>
<value>false</value>
</tagged>
<arcpath id="000" x="475" y="750" curvePoint="false"/>
<arcpath id="001" x="475" y="791" curvePoint="false"/>
<type value="normal"/>
</arc>
<arc id="T32 to r3" source="T32" target="r3">
<graphics/>
<inscription>
<value>Default,1</value>
<graphics/>
</inscription>
<tagged>
<value>false</value>
</tagged>
<arcpath id="000" x="940" y="1061" curvePoint="false"/>
<arcpath id="001" x="891" y="1076" curvePoint="false"/>
<arcpath id="002" x="817" y="1127" curvePoint="false"/>
<type value="normal"/>
</arc>
<arc id="T33 to m4" source="T33" target="m4">
<graphics/>
<inscription>
<value>Default,1</value>
<graphics/>
</inscription>
<tagged>
<value>false</value>
</tagged>
<arcpath id="000" x="940" y="941" curvePoint="false"/>
<arcpath id="001" x="821" y="956" curvePoint="false"/>
<arcpath id="002" x="810" y="986" curvePoint="false"/>
<type value="normal"/>
</arc>
<arc id="T34 to r2" source="T34" target="r2">
<graphics/>
<inscription>
<value>Default,1</value>
<graphics/>
</inscription>
<tagged>
<value>false</value>
</tagged>
<arcpath id="000" x="940" y="851" curvePoint="false"/>
<arcpath id="001" x="791" y="851" curvePoint="false"/>
<arcpath id="002" x="610" y="892" curvePoint="false"/>
<type value="normal"/>
</arc>
<arc id="T35 to m3" source="T35" target="m3">
<graphics/>
<inscription>
<value>Default,1</value>
<graphics/>
</inscription>
<tagged>
<value>false</value>
</tagged>
<arcpath id="000" x="940" y="746" curvePoint="false"/>
<arcpath id="001" x="891" y="761" curvePoint="false"/>
<arcpath id="002" x="818" y="798" curvePoint="false"/>
<type value="normal"/>
</arc>
<arc id="T36 to P27" source="T36" target="P27">
<graphics/>
<inscription>
<value>Default,1</value>
<graphics/>
</inscription>
<tagged>
<value>false</value>
</tagged>
<arcpath id="000" x="970" y="656" curvePoint="false"/>
<arcpath id="001" x="1128" y="610" curvePoint="false"/>
<arcpath id="002" x="1200" y="892" curvePoint="false"/>
<type value="normal"/>
</arc>
<arc id="T36 to P29" source="T36" target="P29">
<graphics/>
<inscription>
<value>Default,1</value>
<graphics/>
</inscription>
<tagged>
<value>false</value>
</tagged>
<arcpath id="000" x="955" y="650" curvePoint="false"/>
<arcpath id="001" x="955" y="587" curvePoint="false"/>
<type value="normal"/>
</arc>
<arc id="T36 to P30" source="T36" target="P30">
<graphics/>
<inscription>
<value>Default,1</value>
<graphics/>
</inscription>
<tagged>
<value>false</value>
</tagged>
<arcpath id="000" x="970" y="656" curvePoint="false"/>
<arcpath id="001" x="1011" y="656" curvePoint="false"/>
<arcpath id="002" x="1056" y="656" curvePoint="false"/>
<arcpath id="003" x="1060" y="911" curvePoint="false"/>
<type value="normal"/>
</arc>
<arc id="T36 to r1" source="T36" target="r1">
<graphics/>
<inscription>
<value>Default,1</value>
<graphics/>
</inscription>
<tagged>
<value>false</value>
</tagged>
<arcpath id="000" x="940" y="656" curvePoint="false"/>
<arcpath id="001" x="891" y="656" curvePoint="false"/>
<arcpath id="002" x="818" y="693" curvePoint="false"/>
<type value="normal"/>
</arc>
<arc id="T3 to m3" source="T3" target="m3">
<graphics/>
<inscription>
<value>Default,1</value>
<graphics/>
</inscription>
<tagged>
<value>false</value>
</tagged>
<arcpath id="000" x="730" y="851" curvePoint="false"/>
<arcpath id="001" x="761" y="851" curvePoint="false"/>
<arcpath id="002" x="795" y="816" curvePoint="false"/>
<type value="normal"/>
</arc>
<arc id="T3 to P4" source="T3" target="P15">
<graphics/>
<inscription>
<value>Default,1</value>
<graphics/>
</inscription>
<tagged>
<value>false</value>
</tagged>
<arcpath id="000" x="715" y="855" curvePoint="false"/>
<arcpath id="001" x="715" y="881" curvePoint="false"/>
<type value="normal"/>
</arc>
<arc id="T4 to P5" source="T13" target="P14">
<graphics/>
<inscription>
<value>Default,1</value>
<graphics/>
</inscription>
<tagged>
<value>false</value>
</tagged>
<arcpath id="000" x="480" y="856" curvePoint="false"/>
<arcpath id="001" x="477" y="881" curvePoint="false"/>
<type value="normal"/>
</arc>
<arc id="T5 to P3" source="T16" target="P17">
<graphics/>
<inscription>
<value>Default,1</value>
<graphics/>
</inscription>
<tagged>
<value>false</value>
</tagged>
<arcpath id="000" x="715" y="945" curvePoint="false"/>
<arcpath id="001" x="715" y="986" curvePoint="false"/>
<type value="normal"/>
</arc>
<arc id="T6 to P2" source="T15" target="P16">
<graphics/>
<inscription>
<value>Default,1</value>
<graphics/>
</inscription>
<tagged>
<value>false</value>
</tagged>
<arcpath id="000" x="475" y="945" curvePoint="false"/>
<arcpath id="001" x="475" y="986" curvePoint="false"/>
<type value="normal"/>
</arc>
<arc id="T6 to r2" source="T15" target="r2">
<graphics/>
<inscription>
<value>Default,1</value>
<graphics/>
</inscription>
<tagged>
<value>false</value>
</tagged>
<arcpath id="000" x="490" y="941" curvePoint="false"/>
<arcpath id="001" x="582" y="901" curvePoint="false"/>
<type value="normal"/>
</arc>
</net>
</pnml>
